pollination/annual_radiation/__init__.py
pollination/annual_radiation/_raytracing.py
pollination/annual_radiation/entry.py
pollination_annual_radiation-0.1.8.dist-info/LICENSE
pollination_annual_radiation-0.1.8.dist-info/METADATA
pollination_annual_radiation-0.1.8.dist-info/WHEEL
pollination_annual_radiation-0.1.8.dist-info/top_level.txt
pollination_annual_radiation-0.1.8.dist-info/RECORD
