Metadata-Version: 2.1
Name: pollination-annual-radiation
Version: 0.1.8
Summary: Annual radiation recipe for Pollination.
Home-page: https://github.com/pollination/annual-radiation
Author: ladybug-tools
Author-email: info@ladybug.tools
Maintainer: mostapha, ladybug-tools
Maintainer-email: mostapha@ladybug.tools, info@ladybug.tools
License: PolyForm Shield License 1.0.0, https://polyformproject.org/wp-content/uploads/2020/06/PolyForm-Shield-1.0.0.txt
Project-URL: icon, https://raw.githubusercontent.com/ladybug-tools/artwork/master/icons_components/honeybee/png/annualradrecipe.png
Project-URL: docker, https://hub.docker.com/r/ladybugtools/honeybee-radiance
Keywords: honeybee,radiance,ladybug-tools,daylight,annual-radiation
Platform: UNKNOWN
Requires-Dist: pollination-honeybee-radiance (>=0.8.0)
Requires-Dist: pollination-alias (>=0.5.3)
Requires-Dist: pollination-path (>=0.1.3)
